kangas/__init__.py
kangas/_typing.py
kangas/_version.py
kangas/colab_env.py
kangas/kaggle_env.py
kangas/utils.py
kangas/cli/__init__.py
kangas/cli/deploy.py
kangas/cli/export_command.py
kangas/cli/import_command.py
kangas/cli/server.py
kangas/cli/upgrade.py
kangas/cli/utils.py
kangas/cli/viewer.py
kangas/datatypes/__init__.py
kangas/datatypes/audio.py
kangas/datatypes/base.py
kangas/datatypes/colormaps.py
kangas/datatypes/curve.py
kangas/datatypes/datagrid.py
kangas/datatypes/embedding.py
kangas/datatypes/image.py
kangas/datatypes/mask.py
kangas/datatypes/math_3d.py
kangas/datatypes/pointcloud.py
kangas/datatypes/serialize.py
kangas/datatypes/tensor.py
kangas/datatypes/text.py
kangas/datatypes/utils.py
kangas/datatypes/video.py
kangas/frontend/BUILD_ID
kangas/frontend/app-build-manifest.json
kangas/frontend/app-path-routes-manifest.json
kangas/frontend/build-manifest.json
kangas/frontend/export-marker.json
kangas/frontend/images-manifest.json
kangas/frontend/next-server.js.nft.json
kangas/frontend/package.json
kangas/frontend/prerender-manifest.json
kangas/frontend/react-loadable-manifest.json
kangas/frontend/required-server-files.json
kangas/frontend/routes-manifest.json
kangas/frontend/trace
kangas/frontend/server/app-paths-manifest.json
kangas/frontend/server/client-reference-manifest.js
kangas/frontend/server/client-reference-manifest.json
kangas/frontend/server/flight-server-css-manifest.js
kangas/frontend/server/flight-server-css-manifest.json
kangas/frontend/server/font-loader-manifest.js
kangas/frontend/server/font-loader-manifest.json
kangas/frontend/server/font-manifest.json
kangas/frontend/server/middleware-build-manifest.js
kangas/frontend/server/middleware-manifest.json
kangas/frontend/server/middleware-react-loadable-manifest.js
kangas/frontend/server/pages-manifest.json
kangas/frontend/server/server-reference-manifest.js
kangas/frontend/server/server-reference-manifest.json
kangas/frontend/server/webpack-api-runtime.js
kangas-2.4.11.dist-info/METADATA
kangas-2.4.11.dist-info/WHEEL
kangas-2.4.11.dist-info/entry_points.txt
kangas-2.4.11.dist-info/top_level.txt
kangas-2.4.11.dist-info/RECORD
