Metadata-Version: 2.1
Name: kangas
Version: 2.4.11
Summary: Tool for exploring columnar data, including multimedia
Home-page: https://github.com/comet-ml/kangas
Author: Kangas Development Team
License: MIT License
Keywords: data science,python,machine learning
Platform: Linux
Platform: Mac OS X
Platform: Windows
Classifier: License :: OSI Approved :: MIT License
Classifier: Programming Language :: Python
Classifier: Programming Language :: Python :: 3
Classifier: Programming Language :: Python :: 3.7
Classifier: Programming Language :: Python :: 3.8
Classifier: Programming Language :: Python :: 3.9
Classifier: Programming Language :: Python :: 3.10
Classifier: Framework :: Jupyter
Requires-Python: >=3.7
Requires-Dist: Pillow
Requires-Dist: astor
Requires-Dist: click
Requires-Dist: flask>=2.2
Requires-Dist: flask-caching
Requires-Dist: marko
Requires-Dist: matplotlib
Requires-Dist: nodejs-bin==16.15.1a4
Requires-Dist: numpy
Requires-Dist: psutil
Requires-Dist: pyngrok
Requires-Dist: requests
Requires-Dist: scikit-learn
Requires-Dist: scipy
Requires-Dist: waitress
